Metadata-Version: 2.1
Name: jaxampler
Version: 0.0.7
Summary: A JAX-based statistical sampling toolkit
Author-email: Meesum Qazalbash <meesumqazalbash@gmail.com>
Maintainer-email: Meesum Qazalbash <meesumqazalbash@gmail.com>
License: Apache License
Project-URL: Homepage, https://github.com/Qazalbash/jaxampler
Project-URL: Issues, https://github.com/Qazalbash/jaxampler/issues
Project-URL: Discussion, https://github.com/Qazalbash/jaxampler/discussions
Project-URL: Changelog, https://github.com/Qazalbash/jaxampler/blob/master/CHANGELOG.md
Keywords: jax,statistics,optimization,sampler,sampling,mcmc,hmc,monte-carlo,markov-chain,scientific
Classifier: Development Status :: 3 - Alpha
Classifier: Programming Language :: Python :: 3
Classifier: Programming Language :: Python :: 3.10
Classifier: Programming Language :: Python :: 3.11
Classifier: License :: OSI Approved :: Apache Software License
Classifier: Operating System :: POSIX :: Linux
Requires-Python: >=3.10
License-File: LICENSE
Requires-Dist: jax >=0.4.0
Requires-Dist: jaxlib >=0.4.0
Requires-Dist: typing-extensions >=4.5.0
Requires-Dist: jaxtyping >=0.2.24
Requires-Dist: matplotlib >=3.8.0
Requires-Dist: setuptools
Requires-Dist: tfp-nightly
Requires-Dist: tqdm
Requires-Dist: twine
Requires-Dist: wheel
